[
  {
    "id": 0,
    "name": "Content Sections",
    "variations": [
      {
        "id": 0,
        "name": "Variation A",
        "image": "/slices-thumbnails/a.png"
      },
      {
        "id": 1,
        "name": "Variation A",
        "image": "/slices-thumbnails/a.png"
      }
    ]
  },
  {
    "id": 1,
    "name": "Hero Sections",
    "variations": [
      {
        "id": 0,
        "name": "Variation A",
        "image": "/slices-thumbnails/a.png"
      },
      {
        "id": 1,
        "name": "Variation A",
        "image": "/slices-thumbnails/a.png"
      }
    ]
  },
  {
    "id": 2,
    "name": "Pricing Sections",
    "variations": [
      {
        "id": 1,
        "name": "Variation A",
        "image": "/slices-thumbnails/a.png"
      }
    ]
  },
  {
    "id": 3,
    "name": "FAQs Sections",
    "variations": [
      {
        "id": 0,
        "name": "Variation A",
        "image": "/slices-thumbnails/a.png"
      },
      {
        "id": 1,
        "name": "Variation A",
        "image": "/slices-thumbnails/a.png"
      }
    ]
  }
]
